kr_holidays/__init__.py
kr_holidays/core.py
kr_holidays/data.py
kr_holidays/utils.py
kr_holidays/data/holidays_2000.json
kr_holidays/data/holidays_2001.json
kr_holidays/data/holidays_2002.json
kr_holidays/data/holidays_2003.json
kr_holidays/data/holidays_2004.json
kr_holidays/data/holidays_2005.json
kr_holidays/data/holidays_2006.json
kr_holidays/data/holidays_2007.json
kr_holidays/data/holidays_2008.json
kr_holidays/data/holidays_2009.json
kr_holidays/data/holidays_2010.json
kr_holidays/data/holidays_2011.json
kr_holidays/data/holidays_2012.json
kr_holidays/data/holidays_2013.json
kr_holidays/data/holidays_2014.json
kr_holidays/data/holidays_2015.json
kr_holidays/data/holidays_2016.json
kr_holidays/data/holidays_2017.json
kr_holidays/data/holidays_2018.json
kr_holidays/data/holidays_2019.json
kr_holidays/data/holidays_2020.json
kr_holidays/data/holidays_2021.json
kr_holidays/data/holidays_2022.json
kr_holidays/data/holidays_2023.json
kr_holidays/data/holidays_2024.json
kr_holidays/data/holidays_2025.json
kr_holidays/data/holidays_2026.json
kr_holidays/data/holidays_2027.json
kr_holidays/data/holidays_2028.json
kr_holidays/data/holidays_2029.json
kr_holidays/data/holidays_2030.json
kr_holidays/data/holidays_2031.json
kr_holidays/data/holidays_2032.json
kr_holidays/data/holidays_2033.json
kr_holidays/data/holidays_2034.json
kr_holidays/data/holidays_2035.json
kr_holidays/data/holidays_2036.json
kr_holidays/data/holidays_2037.json
kr_holidays/data/holidays_2038.json
kr_holidays/data/holidays_2039.json
kr_holidays/data/holidays_2040.json
kr_holidays/data/holidays_2041.json
kr_holidays/data/holidays_2042.json
kr_holidays/data/holidays_2043.json
kr_holidays/data/holidays_2044.json
kr_holidays/data/holidays_2045.json
kr_holidays/data/holidays_2046.json
kr_holidays/data/holidays_2047.json
kr_holidays/data/holidays_2048.json
kr_holidays/data/holidays_2049.json
kr_holidays/data/holidays_2050.json
kr_holidays-1.0.0.dist-info/METADATA
kr_holidays-1.0.0.dist-info/WHEEL
kr_holidays-1.0.0.dist-info/licenses/LICENSE
kr_holidays-1.0.0.dist-info/RECORD
