Metadata-Version: 2.4
Name: kr_holidays
Version: 1.0.0
Summary: 한국 휴일/공휴일/대체공휴일 정보를 제공하는 Python 패키지
Project-URL: Documentation, https://github.com/g-rebels/kr-holiday/blob/master/README.md
Project-URL: Repository, https://github.com/g-rebels/kr-holiday.git
Project-URL: Bug Tracker, https://github.com/g-rebels/kr-holiday/issues
Author-email: basedocker <oasisc1208@icloud.com>
License-File: LICENSE
Keywords: calendar,holidays,korean,공휴일,대체공휴일,주말,캘린더
Classifier: Development Status :: 4 - Beta
Classifier: Intended Audience :: Developers
Classifier: License :: OSI Approved :: MIT License
Classifier: Natural Language :: Korean
Classifier: Operating System :: OS Independent
Classifier: Programming Language :: Python :: 3
Classifier: Programming Language :: Python :: 3.8
Classifier: Programming Language :: Python :: 3.9
Classifier: Programming Language :: Python :: 3.10
Classifier: Programming Language :: Python :: 3.11
Classifier: Programming Language :: Python :: 3.12
Classifier: Topic :: Office/Business :: Scheduling
Classifier: Topic :: Software Development :: Libraries :: Python Modules
Classifier: Topic :: Software Development :: Localization
Classifier: Typing :: Typed
Requires-Python: >=3.8
